LICENSE
MANIFEST.in
README.rst
mkfanstaticsymlink.py
runtests.py
setup.py
fanstatic/__init__.py
fanstatic/checksum.py
fanstatic/codegen.py
fanstatic/config.py
fanstatic/conftest.py
fanstatic/core.py
fanstatic/test_bundle.py
fanstatic/test_checksum.py
fanstatic/test_codegen.py
fanstatic/test_config.py
fanstatic/test_core.py
fanstatic/test_slot.py
fanstatic_tools.egg-info/PKG-INFO
fanstatic_tools.egg-info/SOURCES.txt
fanstatic_tools.egg-info/dependency_links.txt
fanstatic_tools.egg-info/entry_points.txt
fanstatic_tools.egg-info/not-zip-safe
fanstatic_tools.egg-info/requires.txt
fanstatic_tools.egg-info/top_level.txt