Metadata-Version: 1.0
Name: fanstatic-tools
Version: 0.2
Summary: fanstatic tools
Home-page: http://github.com/MiCHiLU/fanstatic-tools
Author: ENDOH takanao
Author-email: UNKNOWN
License: BSD
Platform: UNKNOWN
Classifier: Programming Language :: Python :: 2.6
Classifier: Programming Language :: Python :: 2.7
Classifier: Programming Language :: Python :: 3.2
Classifier: Programming Language :: Python :: 3.3
Classifier: Programming Language :: Python :: Implementation :: PyPy
